mindello_manager/__init__.py
mindello_manager/main.py
mindello_manager/matterlistener.py
mindello_manager-0.1.2.dist-info/METADATA
mindello_manager-0.1.2.dist-info/WHEEL
mindello_manager-0.1.2.dist-info/entry_points.txt
mindello_manager-0.1.2.dist-info/top_level.txt
mindello_manager-0.1.2.dist-info/RECORD
